[
  {
    "id": "1",
    "name": "Chocolate truffle cake",
     "price": 220,
    "ratings": "★★★★★",
    "ratingsCount": 3725,
    "img": "./images/cake-1.jpg",
     "quantity": 0
  },
  
  {
    "id": "2",
    "name": "Chocolate mud cake",
     "price": 110,
    "ratings": "★★★★",
    "ratingsCount": 3005,
    "img": "./images/cake-2.jpg",
     "quantity": 0
  },
  {
    "id": "3",
    "name": "Srawberry Three Floor cake",
    "price": 550,
    "ratings": "★★★★★",
    "ratingsCount": 4725,
    "img": "./images/cake-3.jpg",
     "quantity": 0
  },
  {
    "id": "4",
    "name": "Chocolate fudge cake",
    "price": 720,
    "ratings": "★★★★",
    "ratingsCount": 5245,
    "img": "./images/cake-4.jpg",
     "quantity": 0
  },
  {
    "id": "5",
    "name": "Chocolate Strawberry fudge cake",
     "price": 420,
    "ratings": "★★★★★",
    "ratingsCount": 2345,
    "img": "./images/cake-5.jpg",
     "quantity": 0
  },
  {
    "id": "6",
    "name": "Vanila Strawberry Cake",
    "seller": "Addidas",
    "price": 150,
    "ratings": "★★★★",
    "ratingsCount": 1632,
    "img": "./images/cake-6.jpg",
     "quantity": 0
  },
  {
    "id": "7",
    "name": "Vanila Cherry Cake",
        "price": 230,
    "ratings": "★★★★",
    "ratingsCount": 2343,
    "img": "./images/cake-7.jpg",
     "quantity": 0
  },
  {
    "id": "8",
    "name": "Chocolate mug cake",
        "price": 110,
    "ratings": "★★★★",
    "ratingsCount": 2134,
    "img": "./images/cake-8.jpg",
     "quantity": 0
  },
  {
    "id": "9",
    "name": "Chocolate Cherry Cake",
        "price": 370,
    "ratings": "★★★★★",
    "ratingsCount": 4725,
    "img": "./images/cake-9.jpg",
     "quantity": 0
  },
  {
    "id": "10",
    "name": "Vanila Wedding Cake",
        "price": 850,
    "ratings": "★★★",
    "ratingsCount": 1345,
    "img": "./images/cake-10.jpg",
     "quantity": 0
  },
  {
    "id": "11",
    "name": "Vanila Fruits Cake",
        "price": 320,
    "ratings": "★★★★",
    "ratingsCount": 5234,
    "img": "./images/cake-11.jpg",
     "quantity": 0
  },
  {
    "id": "12",
    "name": "Chocolate Crown Cake",
    "price": 600,
    "ratings": "★★★★★",
    "ratingsCount": 4231,
    "img": "./images/cake-12.jpg",
     "quantity": 0
  },
  {
    "id": "13",
    "name": "Chocolate 3 layer cake",
     "price": 220,
    "ratings": "★★★★",
    "ratingsCount": 23512,
    "img": "./images/cake-13.jpg",
     "quantity": 0
  }
]
